dynamicpdf_api/__init__.py
dynamicpdf_api/action.py
dynamicpdf_api/additional_resource.py
dynamicpdf_api/additional_resource_type.py
dynamicpdf_api/aes128_security.py
dynamicpdf_api/aes256_security.py
dynamicpdf_api/align.py
dynamicpdf_api/cmyk_color.py
dynamicpdf_api/color.py
dynamicpdf_api/color_space_type.py
dynamicpdf_api/converter_input.py
dynamicpdf_api/dlex_input.py
dynamicpdf_api/dlex_layout.py
dynamicpdf_api/dlex_resource.py
dynamicpdf_api/elements/__init__.py
dynamicpdf_api/elements/aztec_barcode_element.py
dynamicpdf_api/elements/aztec_symbol_size.py
dynamicpdf_api/elements/barcode_element.py
dynamicpdf_api/elements/code11_barcode_element.py
dynamicpdf_api/elements/code128_barcode_element.py
dynamicpdf_api/elements/code25_barcode_element.py
dynamicpdf_api/elements/code39_barcode_element.py
dynamicpdf_api/elements/code93_barcode_element.py
dynamicpdf_api/elements/compaction.py
dynamicpdf_api/elements/data_matrix_barcode_element.py
dynamicpdf_api/elements/data_matrix_encoding_type.py
dynamicpdf_api/elements/data_matrix_function_character.py
dynamicpdf_api/elements/data_matrix_symbol_size.py
dynamicpdf_api/elements/dim2_barcode_element.py
dynamicpdf_api/elements/element.py
dynamicpdf_api/elements/element_placement.py
dynamicpdf_api/elements/element_type.py
dynamicpdf_api/elements/error_correction.py
dynamicpdf_api/elements/gs1_data_bar_barcode_element.py
dynamicpdf_api/elements/gs1_data_bar_type.py
dynamicpdf_api/elements/iata25_barcode_element.py
dynamicpdf_api/elements/image_element.py
dynamicpdf_api/elements/line_element.py
dynamicpdf_api/elements/msi_barcode_check_digit_mode.py
dynamicpdf_api/elements/msi_barcode_element.py
dynamicpdf_api/elements/page_numbering_element.py
dynamicpdf_api/elements/pdf417_barcode_element.py
dynamicpdf_api/elements/qr_code_element.py
dynamicpdf_api/elements/qr_code_fnc1.py
dynamicpdf_api/elements/rectangle_element.py
dynamicpdf_api/elements/stacked_gs1_data_bar_barcode_element.py
dynamicpdf_api-1.7.0.dist-info/METADATA
dynamicpdf_api-1.7.0.dist-info/WHEEL
dynamicpdf_api-1.7.0.dist-info/RECORD
