Metadata-Version: 2.1
Name: dynamicpdf-api
Version: 1.7.0
Summary: A Python Client API that uses the DynamicPDF API to create, merge, split, form fill, stamp, secure/encrypt PDF documents and convert HTML, Word docuements to PDFs.
Home-page: https://dpdf.io/
License: MIT
Keywords: PDF,Create,Merge,Split,Fill,Stamp,Secure,Encrypt,Watermark,REST API,Html to PDF,Word to PDF,Image to PDF,Convert
Author: ceTe Software
Author-email: info@dynamicpdf.com
Requires-Python: >=3.7,<4.0
Classifier: License :: OSI Approved :: MIT License
Classifier: Programming Language :: Python :: 3
Classifier: Programming Language :: Python :: 3.7
Classifier: Programming Language :: Python :: 3.8
Classifier: Programming Language :: Python :: 3.9
Classifier: Programming Language :: Python :: 3.10
Classifier: Programming Language :: Python :: 3.11
Requires-Dist: requests (>=2.0.0,<3.0.0)
Project-URL: Documentation, https://dpdf.io/docs/
Project-URL: Repository, https://github.com/dynamicpdf-api/python-client.git
